<?xml version="1.0" encoding="utf-8" ?><dwsync><file name="echarts.cfm" server="52.34.241.55:22//waterbidtracker.com/" local="3601469580" remote="3601469580" Dst="-1" /><file name="niche.cfm" server="52.34.241.55:22//waterbidtracker.com/" local="3603453660" remote="3603453660" Dst="-1" /><file name="pdf.cfm" server="52.34.241.55:22//waterbidtracker.com/" local="3601659120" remote="3601659120" Dst="-1" /><file name="pdf_old.cfm" server="52.34.241.55:22//waterbidtracker.com/" local="3601469160" remote="3601469160" Dst="-1" /><file name="process.cfm" server="52.34.241.55:22//waterbidtracker.com/" local="3601659120" remote="3601659120" Dst="-1" /><file name="solr_results_compare.cfm" server="52.34.241.55:22//waterbidtracker.com/" local="3608901960" remote="3608901960" Dst="-1" /><file name="solrCompare.cfm" server="52.34.241.55:22//waterbidtracker.com/" local="3608900940" remote="3608900940" Dst="-1" /><file name="solrTime.cfm" server="52.34.241.55:22//waterbidtracker.com/" local="3610714740" remote="3610714740" Dst="-1" /><file name="test.cfm" server="52.34.241.55:22//waterbidtracker.com/" local="3601572540" remote="3601572540" Dst="-1" /></dwsync>