<?xml version="1.0" encoding="utf-8" ?><dwsync><file name="Application-old.cfc" server="52.34.241.55:22//360.paintbidtracker.com/" local="3593538528" remote="3556552140" Dst="-1" /><file name="filter_inc.cfm" server="52.34.241.55:22//360.paintbidtracker.com/" local="3593538529" remote="3556552140" Dst="-1" /><file name="filter_modal_inc.cfm" server="52.34.241.55:22//360.paintbidtracker.com/" local="3593538529" remote="3556552140" Dst="-1" /><file name="filter_modal_profile_inc.cfm" server="52.34.241.55:22//360.paintbidtracker.com/" local="3593538529" remote="3556552140" Dst="-1" /><file name="index.cfm" server="52.34.241.55:22//360.paintbidtracker.com/" local="3593538533" remote="3590764500" Dst="-1" /><file name="main_inc.cfm" server="52.34.241.55:22//360.paintbidtracker.com/" local="3593538533" remote="3570630900" Dst="-1" /><file name="test_select.cfm" server="52.34.241.55:22//360.paintbidtracker.com/" local="3593538533" remote="3556552140" Dst="-1" /><file name="test.cfm" server="52.34.241.55:22//360.paintbidtracker.com/" local="3593538533" remote="3556552140" Dst="-1" /><file name="web.config" server="52.34.241.55:22//360.paintbidtracker.com/" local="3593538534" remote="3556552140" Dst="-1" /><file name="_Application.cfc" server="52.34.241.55:22//360.paintbidtracker.com/" local="3593538534" remote="3590590200" Dst="-1" /></dwsync>